setup.py
django_easydump.egg-info/PKG-INFO
django_easydump.egg-info/SOURCES.txt
django_easydump.egg-info/dependency_links.txt
django_easydump.egg-info/requires.txt
django_easydump.egg-info/top_level.txt
easydump/__init__.py
easydump/dumpers.py
easydump/mixins.py
easydump/utils.py
easydump/management/__init__.py
easydump/management/commands/__init__.py
easydump/management/commands/load_dump.py
easydump/management/commands/make_dump.py
easydump/management/commands/rotate_dumps.py