Metadata-Version: 1.0
Name: django-easydump
Version: 0.2.4-
Summary: Easily load database snapshots across deployments
Home-page: http://priestc.github.com/django-easydump/
Author: Chris Priest
Author-email: cp368202@ohiou.edu
License: UNKNOWN
Keywords: django dump database
Platform: UNKNOWN
Classifier: Development Status :: 3 - Alpha
Classifier: Intended Audience :: Developers
Classifier: Topic :: Software Development :: Libraries :: Python Modules
Classifier: Environment :: Web Environment
Classifier: Topic :: Internet
Classifier: Operating System :: OS Independent
Classifier: Programming Language :: Python
Classifier: Framework :: Django
